configs/__init__.py
pykt/__init__.py
pykt/config/__init__.py
pykt/config/config.py
pykt/datasets/__init__.py
pykt/datasets/data_loader.py
pykt/datasets/dkt_forget_dataloader.py
pykt/datasets/init_dataset.py
pykt/datasets/lpkt_dataloader.py
pykt/datasets/lpkt_utils.py
pykt/datasets/que_data_loader.py
pykt/models/__init__.py
pykt/models/akt.py
pykt/models/akt_que.py
pykt/models/atkt.py
pykt/models/deep_irt.py
pykt/models/dkt.py
pykt/models/dkt_forget.py
pykt/models/dkt_plus.py
pykt/models/dkt_que.py
pykt/models/dkvmn.py
pykt/models/evaluate_model.py
pykt/models/gkt.py
pykt/models/gkt_utils.py
pykt/models/hawkes.py
pykt/models/iekt.py
pykt/models/iekt_ce.py
pykt/models/iekt_utils.py
pykt/models/init_model.py
pykt/models/kqn.py
pykt/models/loss.py
pykt/models/lpkt.py
pykt/models/lpkt_utils.py
pykt/models/qdkt.py
pykt/models/que_base_model.py
pykt/models/saint.py
pykt/models/saint_plus_plus.py
pykt/models/sakt.py
pykt/models/skvmn.py
pykt/models/train_model.py
pykt/models/utils.py
pykt/preprocess/__init__.py
pykt/preprocess/algebra2005_preprocess.py
pykt/preprocess/assist2009_preprocess.py
pykt/preprocess/assist2012_preprocess.py
pykt/preprocess/assist2015_preprocess.py
pykt/preprocess/assist2017_preprocess.py
pykt/preprocess/bridge2algebra2006_preprocess.py
pykt/preprocess/data_proprocess.py
pykt/preprocess/ednet_preprocess.py
pykt/preprocess/junyi2015_preprocess.py
pykt/preprocess/nips_task34_preprocess.py
pykt/preprocess/poj_preprocess.py
pykt/preprocess/slepemapy_preprocess.py
pykt/preprocess/split_datasets.py
pykt/preprocess/split_datasets_que.py
pykt/preprocess/statics2011_preprocess.py
pykt/preprocess/utils.py
pykt/utils/__init__.py
pykt/utils/utils.py
pykt/utils/wandb_utils.py
pykt_toolkit-0.0.38.dist-info/LICENSE
pykt_toolkit-0.0.38.dist-info/METADATA
pykt_toolkit-0.0.38.dist-info/WHEEL
pykt_toolkit-0.0.38.dist-info/top_level.txt
pykt_toolkit-0.0.38.dist-info/RECORD
